Metadata-Version: 2.1
Name: base64u
Version: 1.0
Summary: Base64u - URL-Safe Base64 variant no padding.
Home-page: https://github.com/makarworld/base64u.git
Download-URL: https://github.com/makarworld/base64u/archive/refs/tags/v1.0.zip
Author: abuztrade
Author-email: abuztrade.work@gmail.com
License: MIT License
Classifier: Development Status :: 4 - Beta
Classifier: Topic :: Communications :: Email
Classifier: Operating System :: OS Independent
Classifier: License :: OSI Approved :: MIT License
Classifier: Programming Language :: Python :: 3
Classifier: Programming Language :: Python :: 3.6
Classifier: Programming Language :: Python :: 3.7
Classifier: Programming Language :: Python :: 3.8
Classifier: Programming Language :: Python :: 3.9
Classifier: Programming Language :: Python :: 3.10
Classifier: Intended Audience :: Developers
Classifier: Intended Audience :: Customer Service
Classifier: Intended Audience :: Financial and Insurance Industry
Requires-Python: >=3.6.0
License-File: LICENSE
